odoo8_addon_web_easy_switch_company-8.0.1.0.0.99.dev22-py2.7-nspkg.pth
odoo8_addon_web_easy_switch_company-8.0.1.0.0.99.dev22.dist-info/DESCRIPTION.rst
odoo8_addon_web_easy_switch_company-8.0.1.0.0.99.dev22.dist-info/METADATA
odoo8_addon_web_easy_switch_company-8.0.1.0.0.99.dev22.dist-info/RECORD
odoo8_addon_web_easy_switch_company-8.0.1.0.0.99.dev22.dist-info/WHEEL
odoo8_addon_web_easy_switch_company-8.0.1.0.0.99.dev22.dist-info/metadata.json
odoo8_addon_web_easy_switch_company-8.0.1.0.0.99.dev22.dist-info/namespace_packages.txt
odoo8_addon_web_easy_switch_company-8.0.1.0.0.99.dev22.dist-info/top_level.txt
odoo_addons/web_easy_switch_company/__init__.py
odoo_addons/web_easy_switch_company/__openerp__.py
odoo_addons/web_easy_switch_company/controllers/__init__.py
odoo_addons/web_easy_switch_company/controllers/main.py
odoo_addons/web_easy_switch_company/i18n/am.po
odoo_addons/web_easy_switch_company/i18n/ar.po
odoo_addons/web_easy_switch_company/i18n/ca.po
odoo_addons/web_easy_switch_company/i18n/da.po
odoo_addons/web_easy_switch_company/i18n/de.po
odoo_addons/web_easy_switch_company/i18n/el_GR.po
odoo_addons/web_easy_switch_company/i18n/es.po
odoo_addons/web_easy_switch_company/i18n/es_ES.po
odoo_addons/web_easy_switch_company/i18n/es_MX.po
odoo_addons/web_easy_switch_company/i18n/eu.po
odoo_addons/web_easy_switch_company/i18n/fi.po
odoo_addons/web_easy_switch_company/i18n/fr.po
odoo_addons/web_easy_switch_company/i18n/fr_CA.po
odoo_addons/web_easy_switch_company/i18n/fr_CH.po
odoo_addons/web_easy_switch_company/i18n/fr_FR.po
odoo_addons/web_easy_switch_company/i18n/hr.po
odoo_addons/web_easy_switch_company/i18n/hr_HR.po
odoo_addons/web_easy_switch_company/i18n/it.po
odoo_addons/web_easy_switch_company/i18n/nb.po
odoo_addons/web_easy_switch_company/i18n/nb_NO.po
odoo_addons/web_easy_switch_company/i18n/nl.po
odoo_addons/web_easy_switch_company/i18n/nl_BE.po
odoo_addons/web_easy_switch_company/i18n/nl_NL.po
odoo_addons/web_easy_switch_company/i18n/pt_BR.po
odoo_addons/web_easy_switch_company/i18n/ro.po
odoo_addons/web_easy_switch_company/i18n/sk.po
odoo_addons/web_easy_switch_company/i18n/sl.po
odoo_addons/web_easy_switch_company/i18n/tr.po
odoo_addons/web_easy_switch_company/i18n/tr_TR.po
odoo_addons/web_easy_switch_company/i18n/web_easy_switch_company.pot
odoo_addons/web_easy_switch_company/i18n/zh_CN.po
odoo_addons/web_easy_switch_company/model/__init__.py
odoo_addons/web_easy_switch_company/model/res_company.py
